pyims/__init__.py
pyims/pyims.py
pyims-0.1.2.dist-info/METADATA
pyims-0.1.2.dist-info/RECORD
pyims-0.1.2.dist-info/WHEEL
pyims-0.1.2.dist-info/top_level.txt
