Metadata-Version: 2.1
Name: pyims
Version: 0.1.2
Summary: A python wrapper for the IMS Word Sense Disambiguation tool (Zhong and Ng, 2010)
Home-page: http://github.com/vishnumenon/pyims
Author: Vishnu Menon
Author-email: me@vishnumenon.com
License: MIT
Platform: UNKNOWN
Classifier: Programming Language :: Python :: 3
Classifier: License :: OSI Approved :: MIT License
Classifier: Operating System :: OS Independent
Requires-Dist: nltk
